MANIFEST.in
setup.py
charmrunner/__init__.py
charmrunner/dumpzk.py
charmrunner/env.py
charmrunner/graph.py
charmrunner/loader.py
charmrunner/planner.py
charmrunner/readme.rst
charmrunner/recorder.py
charmrunner/runner.py
charmrunner/sftp.py
charmrunner/snapshot.py
charmrunner/watcher.py
charmrunner.egg-info/PKG-INFO
charmrunner.egg-info/SOURCES.txt
charmrunner.egg-info/dependency_links.txt
charmrunner.egg-info/entry_points.txt
charmrunner.egg-info/requires.txt
charmrunner.egg-info/top_level.txt
charmrunner.egg-info/zip-safe