Metadata-Version: 1.1
Name: charmrunner
Version: 0.2.5
Summary: Tools for automated distributed juju charm testing.
Home-page: http://launchpad.net/charmrunner
Author: Kapil Thangavelu
Author-email: kapil.foss@gmail.com
License: GPL
Platform: UNKNOWN
Classifier: Intended Audience :: Developers
Classifier: Programming Language :: Python
Classifier: Operating System :: OS Independent
